sindit/.gitignore
sindit/initialize_authentication.py
sindit/initialize_kg_connectors.py
sindit/initialize_vault.py
sindit/run_sindit.py
sindit/api/__init__.py
sindit/api/api.py
sindit/api/authentication_endpoints.py
sindit/api/connection_endpoints.py
sindit/api/dataspace_endpoints.py
sindit/api/health_endpoints.py
sindit/api/kg_endpoints.py
sindit/api/kg_relationship_endpoints.py
sindit/api/metamodel_endpoints.py
sindit/api/vault_endpoints.py
sindit/api/workspace_endpoints.py
sindit/authentication/authentication_service.py
sindit/authentication/in_memory.py
sindit/authentication/keycloak.py
sindit/authentication/models.py
sindit/authentication/password_hash.py
sindit/authentication/workspace_service.py
sindit/common/__init__.py
sindit/common/semantic_knowledge_graph/GraphDBPersistenceService.py
sindit/common/semantic_knowledge_graph/SemanticKGPersistenceService.py
sindit/common/semantic_knowledge_graph/__init__.py
sindit/common/semantic_knowledge_graph/rdf_model.py
sindit/common/vault/__init__.py
sindit/common/vault/vault.py
sindit/connectors/README.md
sindit/connectors/__init__.py
sindit/connectors/connector.py
sindit/connectors/connector_factory.py
sindit/connectors/connector_influxdb.py
sindit/connectors/connector_mqtt.py
sindit/connectors/connector_postgresql.py
sindit/connectors/connector_s3.py
sindit/connectors/property_influxdb.py
sindit/connectors/property_mqtt.py
sindit/connectors/property_postgresql.py
sindit/connectors/property_s3.py
sindit/connectors/setup_connectors.py
sindit/dataspace/__init__.py
sindit/dataspace/connector_dataspace.py
sindit/docs/img/sindit_logo.png
sindit/docs/img/sindit_logo_bg_removed.png
sindit/docs/img/sindit_logo_org.png
sindit/docs/img/sindit_logo_with_slogan.png
sindit/environment_and_configuration/config.cfg
sindit/environment_and_configuration/dev_environment_backend.env
sindit/environment_and_configuration/docker_environment_backend.env
sindit/environment_and_configuration/user.json
sindit-2.0.17.dist-info/METADATA
sindit-2.0.17.dist-info/WHEEL
sindit-2.0.17.dist-info/licenses/LICENSE
sindit-2.0.17.dist-info/RECORD
