Metadata-Version: 2.4
Name: sindit
Version: 2.0.17
Summary: SINTEF Digital Twin Framework
Project-URL: Homepage, https://github.com/SINTEF-9012/SINDIT20
Project-URL: Repository, https://github.com/SINTEF-9012/SINDIT20
Author-email: An Lam <an.lam@sintef.no>, Gøran Brekke Svaland <goran.svaland@sintef.no>
License: MIT
License-File: LICENSE
Keywords: digital-twin,framework,sintef
Classifier: License :: OSI Approved :: MIT License
Classifier: Operating System :: OS Independent
Classifier: Programming Language :: Python :: 3
Requires-Python: <3.13,>=3.11
Requires-Dist: bcrypt==4.0.1
Requires-Dist: bleak>=0.22.2
Requires-Dist: boto3>=1.35.54
Requires-Dist: fastapi==0.110.1
Requires-Dist: httpx>=0.26.0
Requires-Dist: hvac==2.2.0
Requires-Dist: influxdb-client>=1.44.0
Requires-Dist: jproperties==2.1.1
Requires-Dist: minio>=7.2.20
Requires-Dist: mkdocs>=1.5.3
Requires-Dist: paho-mqtt>=2.1.0
Requires-Dist: pandas==2.2.2
Requires-Dist: passlib[bcrypt]==1.7.4
Requires-Dist: psycopg2-binary>=2.9.10
Requires-Dist: pyjwt==2.10.1
Requires-Dist: pytest-asyncio>=0.23.8
Requires-Dist: pytest-mock>=3.14.0
Requires-Dist: python-dotenv>=1.0.1
Requires-Dist: python-keycloak>=5.8.1
Requires-Dist: python-multipart==0.0.20
Requires-Dist: rdflib==7.0.0
Requires-Dist: requests>=2.31.0
Requires-Dist: ruuvitag-sensor>=2.3.1
Requires-Dist: tomli>=2.3.0
Requires-Dist: tqdm>=4.66.4
Requires-Dist: uvicorn>=0.29.0
Provides-Extra: dev
Requires-Dist: ipykernel>=6.29.4; extra == 'dev'
Requires-Dist: isort>=5.13.2; extra == 'dev'
Provides-Extra: test
Requires-Dist: coverage-badge>=1.1.0; extra == 'test'
Requires-Dist: coverage>=7.3.2; extra == 'test'
Requires-Dist: pytest>=7.4.3; extra == 'test'
